CHANGELOG.md
machinable/__init__.py
machinable/cli.py
machinable/collection.py
machinable/component.py
machinable/config.py
machinable/element.py
machinable/errors.py
machinable/execution.py
machinable/index.py
machinable/interface.py
machinable/mixin.py
machinable/project.py
machinable/py.typed
machinable/query.py
machinable/schedule.py
machinable/schema.py
machinable/scope.py
machinable/storage.py
machinable/types.py
machinable/utils.py
machinable-4.10.6.dist-info/AUTHORS.md
machinable-4.10.6.dist-info/LICENSE.txt
machinable-4.10.6.dist-info/METADATA
machinable-4.10.6.dist-info/WHEEL
machinable-4.10.6.dist-info/entry_points.txt
machinable-4.10.6.dist-info/RECORD
